setup.cfg
setup.py
cstk/__init__.py
cstk/abstract_models.py
cstk.egg-info/PKG-INFO
cstk.egg-info/SOURCES.txt
cstk.egg-info/dependency_links.txt
cstk.egg-info/entry_points.txt
cstk.egg-info/not-zip-safe
cstk.egg-info/top_level.txt
cstk/localisation/__init__.py
cstk/localisation/admin.py
cstk/localisation/models.py
cstk/localisation/tests.py
cstk/localisation/views.py
cstk/translation/__init__.py
cstk/translation/admin.py
cstk/translation/conf.py
cstk/translation/exceptions.py
cstk/translation/loaders.py
cstk/translation/managers.py
cstk/translation/models.py
cstk/translation/options.py
cstk/translation/patches.py
cstk/translation/query.py
cstk/translation/translator.py
cstk/translation/utils.py
cstk/translation/validation.py