Metadata-Version: 1.0
Name: cstk
Version: 0.1-pre-alpha-1dev
Summary: A set of apps for the Django Framework that does the gruntwork for you.
Home-page: http://www.irondev.org/
Author: Paul O'Connor
Author-email: p@p-ocon.com
License: GPL
Keywords: django localisation translation
Platform: UNKNOWN
